arduinocontrollserver/__init__.py
arduinocontrollserver/arduinocontrollserver.py
arduinocontrollserver/www_data/__init__.py
arduinocontrollserver/www_data/arduinocontrollserver.js
ArduinoControllServer-0.1.1555408086.dist-info/LICENSE.txt
ArduinoControllServer-0.1.1555408086.dist-info/METADATA
ArduinoControllServer-0.1.1555408086.dist-info/WHEEL
ArduinoControllServer-0.1.1555408086.dist-info/top_level.txt
ArduinoControllServer-0.1.1555408086.dist-info/RECORD
