Metadata-Version: 2.1
Name: ArduinoControllServer
Version: 0.1.1555408086
Summary: webframe for arduinocontroller
Home-page: https://github.com/JulianKimmig/arduinocontrollserver
Author: Julian Kimmig
Author-email: julian-kimmig@gmx.net
License: UNKNOWN
Platform: UNKNOWN
Classifier: Programming Language :: Python :: 3
Classifier: License :: OSI Approved :: MIT License
Classifier: Operating System :: OS Independent
